coursescheduler/__init__.py
coursescheduler/constraints.py
coursescheduler/csp.py
coursescheduler/datamodels.py
coursescheduler/models.py
coursescheduler/scheduler.py
coursescheduler/verifyconstraints.py
coursescheduler/temp_json_input/professor_object.json
coursescheduler/temp_json_input/schedule_object.json
coursescheduler-0.1.0.dist-info/LICENSE
coursescheduler-0.1.0.dist-info/METADATA
coursescheduler-0.1.0.dist-info/WHEEL
coursescheduler-0.1.0.dist-info/top_level.txt
coursescheduler-0.1.0.dist-info/RECORD
