Metadata-Version: 2.1
Name: coursescheduler
Version: 0.1.0
Summary: A course scheduler for the software engineering program at UVic. Built for the SENG 499 Summer 2022 project.
Home-page: https://github.com/seng499-company2/algorithm1/
Author: Corey Koelewyn, Spencer Davis, Shea Faigan, Nolan Van Hell, Kiana Pazdernik
Author-email: Corey.Koelewyn@gmail.com, str.davis@gmail.com, stfaigan@gmail.com, nolanvh@live.ca, kianapaz021@gmail.com
Project-URL: Bug Tracker, https://github.com/seng499-company2/algorithm1/issues
Classifier: Programming Language :: Python :: 3
Classifier: License :: OSI Approved :: MIT License
Classifier: Operating System :: POSIX :: Linux
Requires-Python: >=3.9
License-File: LICENSE
